{
  "skeletons": {
    "anotherMenu": [
      "-??wrapper??",
      "--??topM60?topM60AER?",
      "--??floatLeftWrapper??",
      "---??brandWrapper brandWrapper2??",
      "----??brandTitle?aerBrandTitle?",
      "----??brand?aerBrand?",
      "----??brandText?aerBrandText?",
      "----??brandOpts?aerBrandOpts?",
      "---??searchWrapper?afterERSearch?",
      "---??ListWrapper?afterERListWrapper?",
      "----??aList smallpb?afterERList?",
      "--??BoxWrapper handout?afterERBoxWrapper?",
      "---??webminh?afterERInputBox?",
      "---??horizontalLine paddingBottom??"
    ],
    "discover": [
      "-??wrapper??",
      "--??topM60??",
      "--??standardFont?erNavigatorOptionsBox?",
      "--??floatLeftWrapper standardFont?erNavigatorBoxWrapper?",
      "---??brandWrapper?myappletstext?",
      "---??leftWrapper?locListOptionsWrapper1?",
      "---??rightWrapper?locListOptionsWrapper?",
      "---??headerWrapper?locHeader?",
      "---???locListOptionsWrapper0?",
      "---??searchWrapper?appSearch?",
      "---???erNavigatorInputBox?",
      "---???erNavigatorInputText?",
      "---???erNavigatorCheckInBBox?",
      "---???erNavigatorExistsBox?",
      "---??ListWrapper?locList?",
      "--???erNavLocDetails?",
      "--??BoxWrapper handout?erNavigatorDetailsBox?",
      "---???erNavigatorDetailsTitle0?",
      "---?h1??erNavigatorDetailsTitle?",
      "---??assetBox?erAssetBox?",
      "----??assetWrapper?erAssetWrapper?",
      "---??webminh?erNavigatorDetails?",
      "---??horizontalLine paddingBottom??",
      "---???erNavigatorDetailsOptions?"
    ],
    "login": [
      "-??wrapper??",
      "--??topM60??",
      "--???loginInputBoxWrapper?",
      "---??maincanvasImage?maincanvasImage2?",
      "---??titleText?loginInputTitle?",
      "---???loginOptionsBox?",
      "---??loginDiv?loginRegisterBox?",
      "----???loginRegisterBox1?",
      "----???loginRegisterBox2?",
      "---???loginInputBox1W?",
      "----??loginDiv?loginInputBox1?",
      "-----???loginInputBox?",
      "-----???logInButtonBBox?",
      "--???loginDetailsBox?",
      "---???logOutButtonBBox?",
      "---???healthRecordsOptionsBox1?",
      "---???loginInputBoxCP?",
      "---???cpWrapper?",
      "---???loginInputBoxCP1?",
      "--???loginAboutWrapper?",
      "---??horizontalLine paddingBottom??"
    ],
    "notifications": [
      "-??wrapper??",
      "--??topM60??",
      "--??BoxWrapper?notificationsBoxWrapper?",
      "---???notificationsInputBox?",
      "----??brandWrapper brandplain??",
      "-----??brand?notBrand?",
      "-----??brandText?notBrandText?",
      "----??standardFont?notificationsInputBoxOptions?",
      "----???notOptions?",
      "----???theNotText?",
      "----???theNotProText?",
      "---???notificationsDeleteWrapper?",
      "----??standardFont?notificationsDelete?",
      "----??deleteConf standardFont?notificationsDeleteConf?",
      "-----???notificationsDeleteYes?",
      "-----???notificationsDeleteNo?",
      "---??horizontalLine paddingBottom??",
      "--??ListWrapper standardFont?notificationsListWrapper?",
      "---??headerWrapper?notHeader?",
      "---??aList smallpb?notificationsList?",
      "---???loadMoreNot?",
      "---??titleText?notStatus?"
    ],
    "mainMenu": [
      "-??maincanvasImage glyphicon glyphicon-log_book?maincanvasImage?",
      "-??horizontalLine?hlMM?",
      "-??buttonsWrapper3Items?mainmenuButtonsWrapper?",
      "-??logoutFlairBBox?logoutFlairBBox?",
      "-??aVideo?caresVideo?"
    ]
  },
  "bclasses": {
    "mainMenu": "",
    "discover": "",
    "anotherMenu": "",
    "login": "",
    "notifications": ""
  }, 
  "transitions": {
    "mainMenu": "slide-out-left",
    "discover": "slide-out-right",
    "anotherMenu": "slide-out-right",
    "login": "slide-out-right",
    "notifications": "slide-out-right"
  },
  "tooltips":{
    "discover": "Discover",
    "anotherMenu": "Menu Item",
    "login": "Login",
    "notifications": "Alerts"
  },
  "btitles":{
    "discover": "Places",
    "products": "Products",
    "orders": "Orders",
    "generateOrder": "Processing Order",
    "login": "Login",
    "notifications": "Alerts"
  },
  "titles":{
    "discover": "Discover",
    "anotherMenu": "A Menu Item",
    "login": "Login",
    "notifications": "Alerts"
  }
}
